ncopt/__about__.py
ncopt/__init__.py
ncopt/plot_utils.py
ncopt/utils.py
ncopt/functions/__init__.py
ncopt/functions/main.py
ncopt/functions/max_linear.py
ncopt/functions/norm_residual.py
ncopt/functions/quadratic.py
ncopt/functions/rosenbrock.py
ncopt/sqpgs/README.md
ncopt/sqpgs/__init__.py
ncopt/sqpgs/cvxpy_subproblem.py
ncopt/sqpgs/defaults.py
ncopt/sqpgs/main.py
ncopt/sqpgs/osqp_subproblem.py
ncopt-0.2.0.dist-info/METADATA
ncopt-0.2.0.dist-info/WHEEL
ncopt-0.2.0.dist-info/licenses/LICENSE
ncopt-0.2.0.dist-info/RECORD
