Metadata-Version: 2.3
Name: ncopt
Version: 0.2.0
Summary: Constrained optimization for Pytorch using the SQP-GS algorithm.
Project-URL: Documentation, https://github.com/fabian-sp/ncOPT#readme
Project-URL: Issues, https://github.com/fabian-sp/ncOPT/issues
Project-URL: Source, https://github.com/fabian-sp/ncOPT
Author: Philipp Schiele
Author-email: Fabian Schaipp <fabian.schaipp@tum.de>
License-Expression: BSD-3-Clause
License-File: LICENSE
Classifier: Development Status :: 4 - Beta
Classifier: Programming Language :: Python
Classifier: Programming Language :: Python :: 3.9
Classifier: Programming Language :: Python :: 3.10
Classifier: Programming Language :: Python :: 3.11
Classifier: Programming Language :: Python :: 3.12
Classifier: Programming Language :: Python :: Implementation :: CPython
Classifier: Programming Language :: Python :: Implementation :: PyPy
Requires-Python: >=3.9
Requires-Dist: cvxpy-base
Requires-Dist: numpy
Requires-Dist: osqp
Requires-Dist: torch
